{ "date": "05:21AM-November-28-2018",
  "users": [
  { "name": "jsperezg",
    "position": 1,
    "contributions": 770,
    "public": 770,
    "private": 0,
    "bio": "Freelancer, currently full stack developer at @aspgems.",
    "followers": 3,
    "repositories":4,
    "organizations":0,
    "join": "2012-05-03",
    "avatar": ""
  },
  { "name": "budavariam",
    "position": 2,
    "contributions": 1092,
    "public": 727,
    "private": 365,
    "bio": "",
    "followers": 2,
    "repositories":10,
    "organizations":0,
    "join": "2017-11-09",
    "avatar": ""
  },
  { "name": "DanielFinestrat",
    "position": 3,
    "contributions": 701,
    "public": 701,
    "private": 0,
    "bio": "Game Dev. C++. Raknet, Box2D, Bullet Physics, Irrlicht, SFML, etc. Unity and Cocos Creator.",
    "followers": 3,
    "repositories":12,
    "organizations":1,
    "join": "2014-09-29",
    "avatar": ""
  },
  { "name": "lronaldo",
    "position": 4,
    "contributions": 643,
    "public": 643,
    "private": 0,
    "bio": "Game Developer since I was a child ||PhD in Computer Science and Machine Learning ||Innovative teacher by nature ||C/C++, Assembly, Z80, Engineering",
    "followers": 49,
    "repositories":8,
    "organizations":0,
    "join": "2011-11-14",
    "avatar": ""
  },
  { "name": "themarioga",
    "position": 5,
    "contributions": 520,
    "public": 520,
    "private": 0,
    "bio": "Programador de C++ y Javascript. Estudiante de Ingenieria Multimedia en la Universidad de Alicante.",
    "followers": 5,
    "repositories":9,
    "organizations":0,
    "join": "2011-01-12",
    "avatar": ""
  },
  { "name": "joakin",
    "position": 6,
    "contributions": 492,
    "public": 492,
    "private": 0,
    "bio": "",
    "followers": 37,
    "repositories":116,
    "organizations":0,
    "join": "2011-03-08",
    "avatar": ""
  },
  { "name": "PabloLIborra",
    "position": 7,
    "contributions": 484,
    "public": 484,
    "private": 0,
    "bio": "Engineering Multimedia programmer.Interested in Game AI and General Artificial Intelligence.",
    "followers": 3,
    "repositories":11,
    "organizations":0,
    "join": "2017-09-12",
    "avatar": ""
  },
  { "name": "kutyel",
    "position": 8,
    "contributions": 703,
    "public": 476,
    "private": 227,
    "bio": "",
    "followers": 195,
    "repositories":118,
    "organizations":5,
    "join": "2013-07-31",
    "avatar": ""
  },
  { "name": "Alexei-117",
    "position": 9,
    "contributions": 471,
    "public": 389,
    "private": 82,
    "bio": "Engineering Multimedia programmer. Interested in AI fields related to General Artificial Intellgence and gaming AI. My hips dont lie.",
    "followers": 3,
    "repositories":9,
    "organizations":0,
    "join": "2015-09-14",
    "avatar": ""
  },
  { "name": "cbh6",
    "position": 10,
    "contributions": 388,
    "public": 387,
    "private": 1,
    "bio": "Web dev enthusiast. Focusing mainly in JS ecosystem",
    "followers": 13,
    "repositories":29,
    "organizations":0,
    "join": "2014-03-30",
    "avatar": ""
  },
  { "name": "alexjoverm",
    "position": 11,
    "contributions": 366,
    "public": 366,
    "private": 0,
    "bio": "Fullstack enthusiastic developer. Love building stuff and learning every day with new technologies. Martial arts, beers and friends!@Domofera co-creator",
    "followers": 204,
    "repositories":114,
    "organizations":1,
    "join": "2013-10-16",
    "avatar": ""
  },
  { "name": "degoo",
    "position": 12,
    "contributions": 336,
    "public": 336,
    "private": 0,
    "bio": "",
    "followers": 3,
    "repositories":2,
    "organizations":0,
    "join": "2016-02-09",
    "avatar": ""
  },
  { "name": "AmyGwyllion",
    "position": 13,
    "contributions": 333,
    "public": 333,
    "private": 0,
    "bio": "Artist and Game Developer.Studied Multimedia Engineering in Alicante University.",
    "followers": 2,
    "repositories":2,
    "organizations":0,
    "join": "2015-10-19",
    "avatar": ""
  },
  { "name": "igarcia10",
    "position": 14,
    "contributions": 333,
    "public": 333,
    "private": 0,
    "bio": "Java Developer",
    "followers": 5,
    "repositories":25,
    "organizations":0,
    "join": "2018-06-06",
    "avatar": ""
  },
  { "name": "Jesus",
    "position": 15,
    "contributions": 2691,
    "public": 330,
    "private": 2361,
    "bio": "",
    "followers": 14,
    "repositories":34,
    "organizations":1,
    "join": "2008-09-03",
    "avatar": ""
  },
  { "name": "aranchafoz",
    "position": 16,
    "contributions": 478,
    "public": 326,
    "private": 152,
    "bio": "Passionate by native Mobile Development. Software developer and computer engineer. Study at University of Alicante and CityU of Hong Kong",
    "followers": 10,
    "repositories":15,
    "organizations":0,
    "join": "2015-09-20",
    "avatar": ""
  },
  { "name": "tanzwud",
    "position": 17,
    "contributions": 328,
    "public": 321,
    "private": 7,
    "bio": "",
    "followers": 5,
    "repositories":65,
    "organizations":1,
    "join": "2013-09-06",
    "avatar": ""
  },
  { "name": "JesusHF",
    "position": 18,
    "contributions": 368,
    "public": 303,
    "private": 65,
    "bio": "Multimedia Engineer passionate about Game Programming and Design ",
    "followers": 4,
    "repositories":5,
    "organizations":0,
    "join": "2015-09-22",
    "avatar": ""
  },
  { "name": "martinlaizg",
    "position": 19,
    "contributions": 325,
    "public": 302,
    "private": 23,
    "bio": "",
    "followers": 4,
    "repositories":8,
    "organizations":0,
    "join": "2016-01-28",
    "avatar": ""
  },
  { "name": "willworth",
    "position": 20,
    "contributions": 296,
    "public": 296,
    "private": 0,
    "bio": "Javascript (react, node) and python programmer.  Got a project you think I could help with? Im interested in contributing to open source as well as paid work.",
    "followers": 4,
    "repositories":126,
    "organizations":0,
    "join": "2013-07-08",
    "avatar": ""
  },
  { "name": "samgarasx",
    "position": 21,
    "contributions": 284,
    "public": 284,
    "private": 0,
    "bio": "Full Stack Developer.React + Kotlin = &lt;3",
    "followers": 6,
    "repositories":11,
    "organizations":0,
    "join": "2015-05-05",
    "avatar": ""
  },
  { "name": "juliansanchez",
    "position": 22,
    "contributions": 277,
    "public": 277,
    "private": 0,
    "bio": "",
    "followers": 7,
    "repositories":11,
    "organizations":0,
    "join": "2014-09-30",
    "avatar": ""
  },
  { "name": "linuxmaniac",
    "position": 23,
    "contributions": 251,
    "public": 251,
    "private": 0,
    "bio": "",
    "followers": 35,
    "repositories":58,
    "organizations":1,
    "join": "2009-03-13",
    "avatar": ""
  },
  { "name": "aarongarciah",
    "position": 24,
    "contributions": 242,
    "public": 242,
    "private": 0,
    "bio": "",
    "followers": 33,
    "repositories":58,
    "organizations":2,
    "join": "2014-04-08",
    "avatar": ""
  },
  { "name": "Zombispormedio",
    "position": 25,
    "contributions": 239,
    "public": 239,
    "private": 0,
    "bio": "Adventurer. Natural Born Reader. Gambler. Film Watcher. Fullstack Developer. Hacking Rocketeer. Public Enemy. JavaScript Superhero. Golang Master",
    "followers": 20,
    "repositories":48,
    "organizations":0,
    "join": "2013-12-05",
    "avatar": ""
  },
  { "name": "Canocles",
    "position": 26,
    "contributions": 232,
    "public": 232,
    "private": 0,
    "bio": "Student account of @EPSAlicante",
    "followers": 7,
    "repositories":10,
    "organizations":0,
    "join": "2014-04-17",
    "avatar": ""
  },
  { "name": "paveltrufi",
    "position": 27,
    "contributions": 210,
    "public": 210,
    "private": 0,
    "bio": "Spring &amp; GWT developer, mainly.Interested in QA, Team Leading, and Agile Management.",
    "followers": 19,
    "repositories":16,
    "organizations":0,
    "join": "2014-10-08",
    "avatar": ""
  },
  { "name": "deulos",
    "position": 28,
    "contributions": 185,
    "public": 185,
    "private": 0,
    "bio": "",
    "followers": 4,
    "repositories":4,
    "organizations":0,
    "join": "2013-12-19",
    "avatar": ""
  },
  { "name": "alejandromaringomez",
    "position": 29,
    "contributions": 176,
    "public": 176,
    "private": 0,
    "bio": "",
    "followers": 2,
    "repositories":4,
    "organizations":0,
    "join": "2018-02-23",
    "avatar": ""
  },
  { "name": "AlvYuste",
    "position": 30,
    "contributions": 169,
    "public": 169,
    "private": 0,
    "bio": "",
    "followers": 8,
    "repositories":2,
    "organizations":2,
    "join": "2012-11-30",
    "avatar": ""
  },
  { "name": "esaujc",
    "position": 31,
    "contributions": 167,
    "public": 167,
    "private": 0,
    "bio": "",
    "followers": 9,
    "repositories":32,
    "organizations":0,
    "join": "2015-06-04",
    "avatar": ""
  },
  { "name": "Blitzman",
    "position": 32,
    "contributions": 302,
    "public": 164,
    "private": 138,
    "bio": "",
    "followers": 22,
    "repositories":33,
    "organizations":1,
    "join": "2013-01-31",
    "avatar": ""
  },
  { "name": "azogue",
    "position": 33,
    "contributions": 164,
    "public": 164,
    "private": 0,
    "bio": "Industrial engineer who was seduced by the Binary Side and ended up as software project manager. Around here with IoT and home automation stuff, mainly",
    "followers": 12,
    "repositories":36,
    "organizations":0,
    "join": "2014-11-14",
    "avatar": ""
  },
  { "name": "ngryman",
    "position": 34,
    "contributions": 1154,
    "public": 163,
    "private": 991,
    "bio": "",
    "followers": 228,
    "repositories":195,
    "organizations":6,
    "join": "2011-07-03",
    "avatar": ""
  },
  { "name": "cArlitXs",
    "position": 35,
    "contributions": 162,
    "public": 162,
    "private": 0,
    "bio": "GG!",
    "followers": 4,
    "repositories":5,
    "organizations":0,
    "join": "2015-07-12",
    "avatar": ""
  },
  { "name": "hllorens",
    "position": 36,
    "contributions": 158,
    "public": 158,
    "private": 0,
    "bio": "",
    "followers": 5,
    "repositories":14,
    "organizations":0,
    "join": "2012-03-30",
    "avatar": ""
  },
  { "name": "AlexMayol",
    "position": 37,
    "contributions": 156,
    "public": 156,
    "private": 0,
    "bio": "",
    "followers": 2,
    "repositories":29,
    "organizations":0,
    "join": "2015-03-04",
    "avatar": ""
  },
  { "name": "asvetliakov",
    "position": 38,
    "contributions": 155,
    "public": 155,
    "private": 0,
    "bio": "",
    "followers": 17,
    "repositories":77,
    "organizations":2,
    "join": "2014-09-23",
    "avatar": ""
  },
  { "name": "sergionejo",
    "position": 39,
    "contributions": 148,
    "public": 148,
    "private": 0,
    "bio": "",
    "followers": 2,
    "repositories":3,
    "organizations":0,
    "join": "2017-02-20",
    "avatar": ""
  },
  { "name": "alejandroSuch",
    "position": 40,
    "contributions": 147,
    "public": 147,
    "private": 0,
    "bio": "",
    "followers": 17,
    "repositories":82,
    "organizations":0,
    "join": "2009-02-09",
    "avatar": ""
  },
  { "name": "alicemirror",
    "position": 41,
    "contributions": 139,
    "public": 139,
    "private": 0,
    "bio": "Enrico Miglino is a developer, researcher, essayist and technical writer who has worked extensively in many fields of electronics and engineering.",
    "followers": 3,
    "repositories":33,
    "organizations":0,
    "join": "2010-11-03",
    "avatar": ""
  },
  { "name": "StormBytePP",
    "position": 42,
    "contributions": 138,
    "public": 138,
    "private": 0,
    "bio": "",
    "followers": 4,
    "repositories":14,
    "organizations":0,
    "join": "2011-03-13",
    "avatar": ""
  },
  { "name": "samael205",
    "position": 43,
    "contributions": 138,
    "public": 138,
    "private": 0,
    "bio": "",
    "followers": 5,
    "repositories":169,
    "organizations":0,
    "join": "2011-03-03",
    "avatar": ""
  },
  { "name": "alebarbaja",
    "position": 44,
    "contributions": 130,
    "public": 130,
    "private": 0,
    "bio": "CSS lover",
    "followers": 5,
    "repositories":32,
    "organizations":0,
    "join": "2017-05-24",
    "avatar": ""
  },
  { "name": "rpairo",
    "position": 45,
    "contributions": 129,
    "public": 129,
    "private": 0,
    "bio": "",
    "followers": 12,
    "repositories":7,
    "organizations":0,
    "join": "2015-09-05",
    "avatar": ""
  },
  { "name": "noctrog",
    "position": 46,
    "contributions": 121,
    "public": 121,
    "private": 0,
    "bio": "Robotics engineering student",
    "followers": 2,
    "repositories":12,
    "organizations":0,
    "join": "2014-06-30",
    "avatar": ""
  },
  { "name": "miguelcarvajal",
    "position": 47,
    "contributions": 112,
    "public": 112,
    "private": 0,
    "bio": "",
    "followers": 12,
    "repositories":36,
    "organizations":0,
    "join": "2012-04-17",
    "avatar": ""
  },
  { "name": "xoner",
    "position": 48,
    "contributions": 110,
    "public": 110,
    "private": 0,
    "bio": "",
    "followers": 3,
    "repositories":15,
    "organizations":0,
    "join": "2009-10-15",
    "avatar": ""
  },
  { "name": "elguardian",
    "position": 49,
    "contributions": 109,
    "public": 109,
    "private": 0,
    "bio": "",
    "followers": 2,
    "repositories":55,
    "organizations":0,
    "join": "2014-02-08",
    "avatar": ""
  },
  { "name": "pabloppp",
    "position": 50,
    "contributions": 1925,
    "public": 106,
    "private": 1819,
    "bio": "",
    "followers": 15,
    "repositories":46,
    "organizations":0,
    "join": "2013-04-23",
    "avatar": ""
  },
  { "name": "pcristinel",
    "position": 51,
    "contributions": 104,
    "public": 104,
    "private": 0,
    "bio": "Back-End JAVA Developer / Front-End Angular Developer",
    "followers": 4,
    "repositories":13,
    "organizations":0,
    "join": "2018-06-10",
    "avatar": ""
  },
  { "name": "alvarobelmonte",
    "position": 52,
    "contributions": 102,
    "public": 102,
    "private": 0,
    "bio": "",
    "followers": 4,
    "repositories":20,
    "organizations":0,
    "join": "2014-03-06",
    "avatar": ""
  },
  { "name": "Onelio",
    "position": 53,
    "contributions": 100,
    "public": 100,
    "private": 0,
    "bio": "Software Engineering student at the University of Alicante. Usually working with C/C++, Go, Java, C#",
    "followers": 6,
    "repositories":32,
    "organizations":1,
    "join": "2013-11-26",
    "avatar": ""
  },
  { "name": "WedgeSparda",
    "position": 54,
    "contributions": 98,
    "public": 98,
    "private": 0,
    "bio": "Mobile developer and nerd.",
    "followers": 12,
    "repositories":8,
    "organizations":0,
    "join": "2009-01-21",
    "avatar": ""
  },
  { "name": "MaQuiNa1995",
    "position": 55,
    "contributions": 99,
    "public": 98,
    "private": 1,
    "bio": "",
    "followers": 5,
    "repositories":29,
    "organizations":0,
    "join": "2015-12-14",
    "avatar": ""
  },
  { "name": "deniz946",
    "position": 56,
    "contributions": 222,
    "public": 94,
    "private": 128,
    "bio": "Frontend developer",
    "followers": 8,
    "repositories":22,
    "organizations":0,
    "join": "2015-01-10",
    "avatar": ""
  },
  { "name": "sergiuoprea",
    "position": 57,
    "contributions": 93,
    "public": 93,
    "private": 0,
    "bio": "PhD Student at University of Alicante. Focused on deep learning-based video prediction, scene understanding and computer vision.",
    "followers": 2,
    "repositories":15,
    "organizations":1,
    "join": "2013-05-10",
    "avatar": ""
  },
  { "name": "pdrogfer",
    "position": 58,
    "contributions": 122,
    "public": 93,
    "private": 29,
    "bio": "",
    "followers": 5,
    "repositories":82,
    "organizations":0,
    "join": "2013-10-05",
    "avatar": ""
  },
  { "name": "paolaski",
    "position": 59,
    "contributions": 93,
    "public": 93,
    "private": 0,
    "bio": "",
    "followers": 6,
    "repositories":5,
    "organizations":0,
    "join": "2016-01-26",
    "avatar": ""
  },
  { "name": "JuanIzquierdoDomenech",
    "position": 60,
    "contributions": 91,
    "public": 91,
    "private": 0,
    "bio": "",
    "followers": 3,
    "repositories":15,
    "organizations":0,
    "join": "2012-08-06",
    "avatar": ""
  },
  { "name": "terox",
    "position": 61,
    "contributions": 1839,
    "public": 71,
    "private": 1768,
    "bio": "Developer. I do things.",
    "followers": 35,
    "repositories":31,
    "organizations":0,
    "join": "2010-04-25",
    "avatar": ""
  },
  { "name": "npgr",
    "position": 62,
    "contributions": 68,
    "public": 68,
    "private": 0,
    "bio": "Full JS Stack Developer: React.js - Node.js - Sails.js - Polymer.js - Electron - Cordova - SQL  &amp; more...Twitter: @NunoGoncalvesR (JS related Articles)",
    "followers": 2,
    "repositories":14,
    "organizations":0,
    "join": "2015-02-12",
    "avatar": ""
  },
  { "name": "duxtinto",
    "position": 63,
    "contributions": 421,
    "public": 67,
    "private": 354,
    "bio": "",
    "followers": 8,
    "repositories":9,
    "organizations":0,
    "join": "2010-07-15",
    "avatar": ""
  },
  { "name": "boudydegeer",
    "position": 64,
    "contributions": 68,
    "public": 67,
    "private": 1,
    "bio": "FullStack Dev &amp; WebArtisan.Curiosity is my second name, love to play around with new technologies and learn new stuff.Love Laravel, VueJS and the community.",
    "followers": 11,
    "repositories":11,
    "organizations":1,
    "join": "2011-04-26",
    "avatar": ""
  },
  { "name": "serfer2",
    "position": 65,
    "contributions": 67,
    "public": 67,
    "private": 0,
    "bio": "In love with software development. Always curious, always learning, always enjoying ;)",
    "followers": 2,
    "repositories":13,
    "organizations":0,
    "join": "2013-08-09",
    "avatar": ""
  },
  { "name": "revington",
    "position": 66,
    "contributions": 67,
    "public": 66,
    "private": 1,
    "bio": "",
    "followers": 24,
    "repositories":77,
    "organizations":0,
    "join": "2009-06-04",
    "avatar": ""
  },
  { "name": "auveele",
    "position": 67,
    "contributions": 65,
    "public": 65,
    "private": 0,
    "bio": "",
    "followers": 3,
    "repositories":8,
    "organizations":0,
    "join": "2013-11-14",
    "avatar": ""
  },
  { "name": "VictorAlbertos",
    "position": 68,
    "contributions": 2523,
    "public": 64,
    "private": 2459,
    "bio": "Android Architect at Cookpad.",
    "followers": 314,
    "repositories":30,
    "organizations":0,
    "join": "2012-10-21",
    "avatar": ""
  },
  { "name": "jaj712",
    "position": 69,
    "contributions": 64,
    "public": 64,
    "private": 0,
    "bio": "",
    "followers": 4,
    "repositories":4,
    "organizations":0,
    "join": "2018-10-24",
    "avatar": ""
  },
  { "name": "pablobenitogonzalez",
    "position": 70,
    "contributions": 63,
    "public": 63,
    "private": 0,
    "bio": "Java developer",
    "followers": 5,
    "repositories":38,
    "organizations":0,
    "join": "2013-11-23",
    "avatar": ""
  },
  { "name": "jeselxe",
    "position": 71,
    "contributions": 62,
    "public": 62,
    "private": 0,
    "bio": "",
    "followers": 9,
    "repositories":11,
    "organizations":1,
    "join": "2014-06-23",
    "avatar": ""
  },
  { "name": "eljuanchosf",
    "position": 72,
    "contributions": 117,
    "public": 61,
    "private": 56,
    "bio": "Cloud Architect and DevOps Practitioner. Human being of sorts. Proud tanguero.",
    "followers": 17,
    "repositories":62,
    "organizations":1,
    "join": "2010-04-06",
    "avatar": ""
  },
  { "name": "FenixHielo",
    "position": 73,
    "contributions": 61,
    "public": 61,
    "private": 0,
    "bio": "",
    "followers": 2,
    "repositories":3,
    "organizations":0,
    "join": "2016-10-03",
    "avatar": ""
  },
  { "name": "asabirov",
    "position": 74,
    "contributions": 59,
    "public": 59,
    "private": 0,
    "bio": "",
    "followers": 7,
    "repositories":57,
    "organizations":0,
    "join": "2011-04-16",
    "avatar": ""
  },
  { "name": "andresBalanza",
    "position": 75,
    "contributions": 58,
    "public": 58,
    "private": 0,
    "bio": "",
    "followers": 2,
    "repositories":5,
    "organizations":0,
    "join": "2017-01-27",
    "avatar": ""
  },
  { "name": "Pepelux",
    "position": 76,
    "contributions": 57,
    "public": 57,
    "private": 0,
    "bio": "https://www.linkedin.com/in/pepelux/http://blog.pepelux.org",
    "followers": 4,
    "repositories":3,
    "organizations":0,
    "join": "2014-03-12",
    "avatar": ""
  },
  { "name": "jvgranados",
    "position": 77,
    "contributions": 57,
    "public": 57,
    "private": 0,
    "bio": "",
    "followers": 3,
    "repositories":10,
    "organizations":0,
    "join": "2017-01-03",
    "avatar": ""
  },
  { "name": "parequena",
    "position": 78,
    "contributions": 56,
    "public": 56,
    "private": 0,
    "bio": "IT Student.LinkedIn: https://goo.gl/c3RXXKTwitter: https://goo.gl/PqmQMM",
    "followers": 6,
    "repositories":8,
    "organizations":0,
    "join": "2016-09-12",
    "avatar": ""
  },
  { "name": "larryrider",
    "position": 79,
    "contributions": 55,
    "public": 55,
    "private": 0,
    "bio": "Student account of @EPSAlicante",
    "followers": 6,
    "repositories":15,
    "organizations":0,
    "join": "2014-02-28",
    "avatar": ""
  },
  { "name": "rubenmv",
    "position": 80,
    "contributions": 54,
    "public": 54,
    "private": 0,
    "bio": "",
    "followers": 10,
    "repositories":26,
    "organizations":0,
    "join": "2009-03-17",
    "avatar": ""
  },
  { "name": "daniespin",
    "position": 81,
    "contributions": 54,
    "public": 54,
    "private": 0,
    "bio": "",
    "followers": 2,
    "repositories":3,
    "organizations":0,
    "join": "2018-10-25",
    "avatar": ""
  },
  { "name": "Knack",
    "position": 82,
    "contributions": 2544,
    "public": 53,
    "private": 2491,
    "bio": "",
    "followers": 14,
    "repositories":16,
    "organizations":1,
    "join": "2008-09-24",
    "avatar": ""
  },
  { "name": "josemamira",
    "position": 83,
    "contributions": 53,
    "public": 53,
    "private": 0,
    "bio": "My name is Jose Manuel Mira Martinez. I work in University of Alicante as GIS teacher and technical in University of Alicante. I colaborate in @labgeo.",
    "followers": 3,
    "repositories":12,
    "organizations":1,
    "join": "2011-05-18",
    "avatar": ""
  },
  { "name": "alfonsodev",
    "position": 84,
    "contributions": 658,
    "public": 50,
    "private": 608,
    "bio": "Co-Founder at Ghinwa, http://ghinwa.fm Former tech lead at Rocket Internet.",
    "followers": 19,
    "repositories":173,
    "organizations":2,
    "join": "2012-08-10",
    "avatar": ""
  },
  { "name": "yduartep",
    "position": 85,
    "contributions": 50,
    "public": 50,
    "private": 0,
    "bio": "Frontend Architect - Angular fan",
    "followers": 8,
    "repositories":9,
    "organizations":0,
    "join": "2016-12-09",
    "avatar": ""
  },
  { "name": "crossblaim",
    "position": 86,
    "contributions": 46,
    "public": 46,
    "private": 0,
    "bio": "",
    "followers": 46,
    "repositories":32,
    "organizations":0,
    "join": "2008-04-02",
    "avatar": ""
  },
  { "name": "mfernam",
    "position": 87,
    "contributions": 46,
    "public": 46,
    "private": 0,
    "bio": "Developer and GIS specialist. ",
    "followers": 5,
    "repositories":10,
    "organizations":1,
    "join": "2013-10-15",
    "avatar": ""
  },
  { "name": "pauiglesias",
    "position": 88,
    "contributions": 45,
    "public": 45,
    "private": 0,
    "bio": "Freelance developer focused on WordPress plugins, Laravel applications and VueJS components.",
    "followers": 4,
    "repositories":5,
    "organizations":0,
    "join": "2011-11-03",
    "avatar": ""
  },
  { "name": "alberapps",
    "position": 89,
    "contributions": 45,
    "public": 45,
    "private": 0,
    "bio": "",
    "followers": 2,
    "repositories":8,
    "organizations":0,
    "join": "2013-04-19",
    "avatar": ""
  },
  { "name": "vladern",
    "position": 90,
    "contributions": 44,
    "public": 44,
    "private": 0,
    "bio": "I am a student of University of Alicante  of Computer science.",
    "followers": 2,
    "repositories":14,
    "organizations":0,
    "join": "2016-03-04",
    "avatar": ""
  },
  { "name": "Bym24v",
    "position": 91,
    "contributions": 40,
    "public": 40,
    "private": 0,
    "bio": "Programmer / RE",
    "followers": 17,
    "repositories":24,
    "organizations":0,
    "join": "2013-09-09",
    "avatar": ""
  },
  { "name": "JoseVte",
    "position": 92,
    "contributions": 39,
    "public": 39,
    "private": 0,
    "bio": "Web developer specialized in Laravel",
    "followers": 8,
    "repositories":25,
    "organizations":0,
    "join": "2013-02-12",
    "avatar": ""
  },
  { "name": "Jmartnz",
    "position": 93,
    "contributions": 35,
    "public": 35,
    "private": 0,
    "bio": "",
    "followers": 8,
    "repositories":5,
    "organizations":0,
    "join": "2014-10-13",
    "avatar": ""
  },
  { "name": "ferminlp93",
    "position": 94,
    "contributions": 35,
    "public": 35,
    "private": 0,
    "bio": "I am a telecommunications engineer and also a passionate data projects.",
    "followers": 6,
    "repositories":12,
    "organizations":0,
    "join": "2017-09-22",
    "avatar": ""
  },
  { "name": "jersiovic",
    "position": 95,
    "contributions": 33,
    "public": 33,
    "private": 0,
    "bio": "",
    "followers": 2,
    "repositories":6,
    "organizations":1,
    "join": "2013-07-05",
    "avatar": ""
  },
  { "name": "jospicant",
    "position": 96,
    "contributions": 33,
    "public": 33,
    "private": 0,
    "bio": "I love electronic systems.I am interested to learn all about electronic systems.I am trying a new free tool call Icestudio for working with FPGAs.",
    "followers": 5,
    "repositories":9,
    "organizations":0,
    "join": "2014-09-07",
    "avatar": ""
  },
  { "name": "xblau",
    "position": 97,
    "contributions": 695,
    "public": 30,
    "private": 665,
    "bio": "",
    "followers": 4,
    "repositories":8,
    "organizations":0,
    "join": "2015-07-30",
    "avatar": ""
  },
  { "name": "periket2000",
    "position": 98,
    "contributions": 28,
    "public": 28,
    "private": 0,
    "bio": "",
    "followers": 7,
    "repositories":28,
    "organizations":0,
    "join": "2009-04-13",
    "avatar": ""
  },
  { "name": "rampa069",
    "position": 99,
    "contributions": 28,
    "public": 28,
    "private": 0,
    "bio": "",
    "followers": 12,
    "repositories":25,
    "organizations":0,
    "join": "2011-08-02",
    "avatar": ""
  },
  { "name": "franktoffel",
    "position": 100,
    "contributions": 28,
    "public": 28,
    "private": 0,
    "bio": "",
    "followers": 37,
    "repositories":28,
    "organizations":1,
    "join": "2013-08-20",
    "avatar": ""
  },
  { "name": "jers0",
    "position": 101,
    "contributions": 64,
    "public": 27,
    "private": 37,
    "bio": "",
    "followers": 2,
    "repositories":17,
    "organizations":0,
    "join": "2015-03-12",
    "avatar": ""
  },
  { "name": "xgalen",
    "position": 102,
    "contributions": 1139,
    "public": 25,
    "private": 1114,
    "bio": "",
    "followers": 14,
    "repositories":19,
    "organizations":1,
    "join": "2012-01-16",
    "avatar": ""
  },
  { "name": "nachosalvador",
    "position": 103,
    "contributions": 32,
    "public": 25,
    "private": 7,
    "bio": "",
    "followers": 3,
    "repositories":11,
    "organizations":1,
    "join": "2014-09-25",
    "avatar": ""
  },
  { "name": "javialm",
    "position": 104,
    "contributions": 24,
    "public": 24,
    "private": 0,
    "bio": "",
    "followers": 2,
    "repositories":7,
    "organizations":0,
    "join": "2016-09-25",
    "avatar": ""
  },
  { "name": "davidpv",
    "position": 105,
    "contributions": 22,
    "public": 22,
    "private": 0,
    "bio": "",
    "followers": 14,
    "repositories":18,
    "organizations":0,
    "join": "2010-06-28",
    "avatar": ""
  },
  { "name": "sorts",
    "position": 106,
    "contributions": 22,
    "public": 21,
    "private": 1,
    "bio": "",
    "followers": 3,
    "repositories":4,
    "organizations":0,
    "join": "2012-01-13",
    "avatar": ""
  },
  { "name": "owenjr",
    "position": 107,
    "contributions": 21,
    "public": 21,
    "private": 0,
    "bio": "Multimedia Engineer at the Polytechnic School of Alicante.",
    "followers": 2,
    "repositories":6,
    "organizations":0,
    "join": "2016-11-05",
    "avatar": ""
  },
  { "name": "Erni",
    "position": 108,
    "contributions": 19,
    "public": 19,
    "private": 0,
    "bio": "",
    "followers": 3,
    "repositories":9,
    "organizations":0,
    "join": "2011-04-12",
    "avatar": ""
  },
  { "name": "drcz",
    "position": 109,
    "contributions": 18,
    "public": 18,
    "private": 0,
    "bio": "",
    "followers": 12,
    "repositories":18,
    "organizations":0,
    "join": "2012-02-03",
    "avatar": ""
  },
  { "name": "JHipolito",
    "position": 110,
    "contributions": 18,
    "public": 18,
    "private": 0,
    "bio": "",
    "followers": 4,
    "repositories":8,
    "organizations":0,
    "join": "2015-12-19",
    "avatar": ""
  },
  { "name": "josejamart",
    "position": 111,
    "contributions": 17,
    "public": 17,
    "private": 0,
    "bio": "",
    "followers": 2,
    "repositories":6,
    "organizations":0,
    "join": "2012-12-03",
    "avatar": ""
  },
  { "name": "davidespihernandez",
    "position": 112,
    "contributions": 16,
    "public": 16,
    "private": 0,
    "bio": "Spanish sofware engineer.I love to solve problems, and I love to learn new things.",
    "followers": 2,
    "repositories":13,
    "organizations":0,
    "join": "2012-10-27",
    "avatar": ""
  },
  { "name": "nachovalera",
    "position": 113,
    "contributions": 22,
    "public": 16,
    "private": 6,
    "bio": "https://gitlab.com/nacho.valeraDeveloper, Cloud Architect. AWS Certified Solutions Architect - Associate. Magento, AWS, Terraform.",
    "followers": 8,
    "repositories":10,
    "organizations":1,
    "join": "2017-03-16",
    "avatar": ""
  },
  { "name": "ferminhg",
    "position": 114,
    "contributions": 15,
    "public": 15,
    "private": 0,
    "bio": "CTO in planetahuerto.es",
    "followers": 6,
    "repositories":28,
    "organizations":0,
    "join": "2011-07-28",
    "avatar": ""
  },
  { "name": "mbernabeu",
    "position": 115,
    "contributions": 15,
    "public": 15,
    "private": 0,
    "bio": "",
    "followers": 7,
    "repositories":8,
    "organizations":1,
    "join": "2014-01-21",
    "avatar": ""
  },
  { "name": "JavierFuentes",
    "position": 116,
    "contributions": 13,
    "public": 13,
    "private": 0,
    "bio": "",
    "followers": 2,
    "repositories":8,
    "organizations":0,
    "join": "2013-10-29",
    "avatar": ""
  },
  { "name": "ChazyTheBest",
    "position": 117,
    "contributions": 12,
    "public": 12,
    "private": 0,
    "bio": "",
    "followers": 4,
    "repositories":18,
    "organizations":1,
    "join": "2011-03-06",
    "avatar": ""
  },
  { "name": "simoean",
    "position": 118,
    "contributions": 12,
    "public": 12,
    "private": 0,
    "bio": "Passionate father, husband and software engineer. Solution &amp; Enterprise architect, technical lead and full stack developer at Unisys. TOGAF &amp; PRINCE2 certified.",
    "followers": 3,
    "repositories":4,
    "organizations":0,
    "join": "2011-04-29",
    "avatar": ""
  },
  { "name": "arubio",
    "position": 119,
    "contributions": 12,
    "public": 12,
    "private": 0,
    "bio": "",
    "followers": 3,
    "repositories":4,
    "organizations":0,
    "join": "2012-10-21",
    "avatar": ""
  },
  { "name": "impreza233",
    "position": 120,
    "contributions": 12,
    "public": 12,
    "private": 0,
    "bio": "Civil Engineer with a dev twist ;)Used to work in Android and UWP apps. ",
    "followers": 2,
    "repositories":5,
    "organizations":0,
    "join": "2017-02-15",
    "avatar": ""
  },
  { "name": "sabuko",
    "position": 121,
    "contributions": 11,
    "public": 11,
    "private": 0,
    "bio": "",
    "followers": 4,
    "repositories":34,
    "organizations":0,
    "join": "2009-04-19",
    "avatar": ""
  },
  { "name": "jaimenj",
    "position": 122,
    "contributions": 11,
    "public": 11,
    "private": 0,
    "bio": "I enjoy programming..",
    "followers": 10,
    "repositories":8,
    "organizations":1,
    "join": "2013-11-27",
    "avatar": ""
  },
  { "name": "kevinc123",
    "position": 123,
    "contributions": 260,
    "public": 11,
    "private": 249,
    "bio": "Im an student of Higher degree of multiplatform application development. Next year I will start the Higher degree of web application development.",
    "followers": 2,
    "repositories":5,
    "organizations":1,
    "join": "2015-08-26",
    "avatar": ""
  },
  { "name": "IsraelIglesiasBIT",
    "position": 124,
    "contributions": 11,
    "public": 11,
    "private": 0,
    "bio": "CTO en Conwork",
    "followers": 3,
    "repositories":4,
    "organizations":1,
    "join": "2016-02-01",
    "avatar": ""
  },
  { "name": "aydevosotros",
    "position": 125,
    "contributions": 10,
    "public": 10,
    "private": 0,
    "bio": "",
    "followers": 5,
    "repositories":18,
    "organizations":0,
    "join": "2012-03-16",
    "avatar": ""
  },
  { "name": "lotelx",
    "position": 126,
    "contributions": 10,
    "public": 10,
    "private": 0,
    "bio": "Computer engineer &amp; transdisciplinar anti-artist.",
    "followers": 6,
    "repositories":2,
    "organizations":0,
    "join": "2012-05-22",
    "avatar": ""
  },
  { "name": "juanpomares",
    "position": 127,
    "contributions": 10,
    "public": 10,
    "private": 0,
    "bio": "",
    "followers": 3,
    "repositories":3,
    "organizations":0,
    "join": "2015-12-18",
    "avatar": ""
  },
  { "name": "hopesend",
    "position": 128,
    "contributions": 9,
    "public": 9,
    "private": 0,
    "bio": "",
    "followers": 3,
    "repositories":18,
    "organizations":0,
    "join": "2014-01-04",
    "avatar": ""
  },
  { "name": "TheDucke",
    "position": 129,
    "contributions": 9,
    "public": 9,
    "private": 0,
    "bio": "Senior Software Developer with +10 years of professional experience. Specialized in .Net Framework projects.Diving into Deep Learning",
    "followers": 3,
    "repositories":7,
    "organizations":0,
    "join": "2015-03-09",
    "avatar": ""
  },
  { "name": "mariogm89",
    "position": 130,
    "contributions": 9,
    "public": 9,
    "private": 0,
    "bio": "Aprendizaje de Desarrollo Web con PHP, WordPress, Prestashop y Marketing Digital",
    "followers": 9,
    "repositories":5,
    "organizations":0,
    "join": "2017-02-20",
    "avatar": ""
  },
  { "name": "guilu",
    "position": 131,
    "contributions": 8,
    "public": 8,
    "private": 0,
    "bio": "",
    "followers": 4,
    "repositories":23,
    "organizations":0,
    "join": "2009-11-24",
    "avatar": ""
  },
  { "name": "Shemes",
    "position": 132,
    "contributions": 7,
    "public": 7,
    "private": 0,
    "bio": "",
    "followers": 5,
    "repositories":3,
    "organizations":1,
    "join": "2009-09-02",
    "avatar": ""
  },
  { "name": "msociety",
    "position": 133,
    "contributions": 7,
    "public": 7,
    "private": 0,
    "bio": "I am schizophrenic.And me too",
    "followers": 11,
    "repositories":13,
    "organizations":0,
    "join": "2011-07-22",
    "avatar": ""
  },
  { "name": "planelles20",
    "position": 134,
    "contributions": 7,
    "public": 7,
    "private": 0,
    "bio": "",
    "followers": 21,
    "repositories":15,
    "organizations":1,
    "join": "2014-11-12",
    "avatar": ""
  },
  { "name": "keropodium",
    "position": 135,
    "contributions": 7,
    "public": 7,
    "private": 0,
    "bio": "",
    "followers": 18,
    "repositories":11,
    "organizations":0,
    "join": "2015-07-02",
    "avatar": ""
  },
  { "name": "jraicr",
    "position": 136,
    "contributions": 6,
    "public": 6,
    "private": 0,
    "bio": "",
    "followers": 4,
    "repositories":8,
    "organizations":0,
    "join": "2011-03-02",
    "avatar": ""
  },
  { "name": "jisbert",
    "position": 137,
    "contributions": 6,
    "public": 6,
    "private": 0,
    "bio": "",
    "followers": 5,
    "repositories":9,
    "organizations":0,
    "join": "2010-09-21",
    "avatar": ""
  },
  { "name": "pacosegovia",
    "position": 138,
    "contributions": 6,
    "public": 6,
    "private": 0,
    "bio": "Front-end en @nitsnets",
    "followers": 7,
    "repositories":4,
    "organizations":0,
    "join": "2013-09-26",
    "avatar": ""
  },
  { "name": "Grunmir",
    "position": 139,
    "contributions": 6,
    "public": 6,
    "private": 0,
    "bio": "",
    "followers": 3,
    "repositories":5,
    "organizations":0,
    "join": "2014-06-04",
    "avatar": ""
  },
  { "name": "jst7",
    "position": 140,
    "contributions": 10,
    "public": 6,
    "private": 4,
    "bio": "",
    "followers": 4,
    "repositories":10,
    "organizations":0,
    "join": "2014-06-06",
    "avatar": ""
  },
  { "name": "pedperpat",
    "position": 141,
    "contributions": 6,
    "public": 6,
    "private": 0,
    "bio": "",
    "followers": 12,
    "repositories":12,
    "organizations":0,
    "join": "2015-09-14",
    "avatar": ""
  },
  { "name": "msanpe",
    "position": 142,
    "contributions": 6,
    "public": 6,
    "private": 0,
    "bio": "",
    "followers": 13,
    "repositories":13,
    "organizations":0,
    "join": "2015-09-30",
    "avatar": ""
  },
  { "name": "jacinmontava",
    "position": 143,
    "contributions": 5,
    "public": 5,
    "private": 0,
    "bio": "",
    "followers": 2,
    "repositories":17,
    "organizations":0,
    "join": "2012-11-19",
    "avatar": ""
  },
  { "name": "damianmcdonald",
    "position": 144,
    "contributions": 5,
    "public": 5,
    "private": 0,
    "bio": "",
    "followers": 11,
    "repositories":25,
    "organizations":0,
    "join": "2015-07-04",
    "avatar": ""
  },
  { "name": "Reyeselda95",
    "position": 145,
    "contributions": 5,
    "public": 5,
    "private": 0,
    "bio": "Computer Engineering Student and artist by hobby. Loving animation since 1995.",
    "followers": 17,
    "repositories":25,
    "organizations":0,
    "join": "2016-09-12",
    "avatar": ""
  },
  { "name": "davilious",
    "position": 146,
    "contributions": 4,
    "public": 4,
    "private": 0,
    "bio": "Frontend en BeBanjo, entusiasta de Javascript, amante de CSS y apasionado del mundo Ruby on Rails.",
    "followers": 9,
    "repositories":33,
    "organizations":0,
    "join": "2011-07-31",
    "avatar": ""
  },
  { "name": "juaruipi",
    "position": 147,
    "contributions": 1938,
    "public": 4,
    "private": 1934,
    "bio": "",
    "followers": 3,
    "repositories":7,
    "organizations":0,
    "join": "2013-05-23",
    "avatar": ""
  },
  { "name": "jruzafa",
    "position": 148,
    "contributions": 3,
    "public": 3,
    "private": 0,
    "bio": "developer at Devopensource.com",
    "followers": 64,
    "repositories":49,
    "organizations":1,
    "join": "2010-02-23",
    "avatar": ""
  },
  { "name": "Llop1s",
    "position": 149,
    "contributions": 3,
    "public": 3,
    "private": 0,
    "bio": "",
    "followers": 5,
    "repositories":9,
    "organizations":0,
    "join": "2011-01-12",
    "avatar": ""
  },
  { "name": "heliosam",
    "position": 150,
    "contributions": 3,
    "public": 3,
    "private": 0,
    "bio": "",
    "followers": 14,
    "repositories":8,
    "organizations":0,
    "join": "2013-07-18",
    "avatar": ""
  },
  { "name": "escorponox",
    "position": 151,
    "contributions": 4,
    "public": 3,
    "private": 1,
    "bio": "",
    "followers": 29,
    "repositories":32,
    "organizations":0,
    "join": "2013-07-31",
    "avatar": ""
  },
  { "name": "jmahiques",
    "position": 152,
    "contributions": 3,
    "public": 3,
    "private": 0,
    "bio": "",
    "followers": 7,
    "repositories":7,
    "organizations":0,
    "join": "2013-09-06",
    "avatar": ""
  },
  { "name": "AngelVB",
    "position": 153,
    "contributions": 3,
    "public": 3,
    "private": 0,
    "bio": "",
    "followers": 14,
    "repositories":12,
    "organizations":0,
    "join": "2014-10-17",
    "avatar": ""
  },
  { "name": "adririquelme",
    "position": 154,
    "contributions": 3,
    "public": 3,
    "private": 0,
    "bio": "",
    "followers": 2,
    "repositories":2,
    "organizations":0,
    "join": "2014-11-08",
    "avatar": ""
  },
  { "name": "javiererrogarcia",
    "position": 155,
    "contributions": 3,
    "public": 3,
    "private": 0,
    "bio": "Java developer trying to improve my Big Data skills",
    "followers": 2,
    "repositories":2,
    "organizations":0,
    "join": "2016-09-25",
    "avatar": ""
  },
  { "name": "olivermontes",
    "position": 156,
    "contributions": 2,
    "public": 2,
    "private": 0,
    "bio": "CEO at @DevopensourceTeam Web developer &amp; Ecommerce fanatic!",
    "followers": 59,
    "repositories":20,
    "organizations":1,
    "join": "2010-01-06",
    "avatar": ""
  },
  { "name": "Alwaison",
    "position": 157,
    "contributions": 2,
    "public": 2,
    "private": 0,
    "bio": "",
    "followers": 12,
    "repositories":10,
    "organizations":0,
    "join": "2010-06-03",
    "avatar": ""
  },
  { "name": "shadowlink",
    "position": 158,
    "contributions": 2,
    "public": 2,
    "private": 0,
    "bio": "",
    "followers": 2,
    "repositories":9,
    "organizations":0,
    "join": "2010-07-30",
    "avatar": ""
  },
  { "name": "jgmullor",
    "position": 159,
    "contributions": 493,
    "public": 2,
    "private": 491,
    "bio": "",
    "followers": 6,
    "repositories":35,
    "organizations":0,
    "join": "2012-01-03",
    "avatar": ""
  },
  { "name": "GianniPDF",
    "position": 160,
    "contributions": 2,
    "public": 2,
    "private": 0,
    "bio": "",
    "followers": 3,
    "repositories":2,
    "organizations":0,
    "join": "2012-01-21",
    "avatar": ""
  },
  { "name": "reimago",
    "position": 161,
    "contributions": 2,
    "public": 2,
    "private": 0,
    "bio": "",
    "followers": 5,
    "repositories":7,
    "organizations":0,
    "join": "2013-05-13",
    "avatar": ""
  },
  { "name": "vginert",
    "position": 162,
    "contributions": 2,
    "public": 2,
    "private": 0,
    "bio": "",
    "followers": 4,
    "repositories":13,
    "organizations":0,
    "join": "2014-04-02",
    "avatar": ""
  },
  { "name": "empanadix",
    "position": 163,
    "contributions": 2,
    "public": 2,
    "private": 0,
    "bio": "",
    "followers": 3,
    "repositories":3,
    "organizations":0,
    "join": "2015-10-08",
    "avatar": ""
  },
  { "name": "adrianamat6",
    "position": 164,
    "contributions": 2,
    "public": 2,
    "private": 0,
    "bio": "Chemical Engineer at University of Alicante. ",
    "followers": 2,
    "repositories":8,
    "organizations":0,
    "join": "2017-05-17",
    "avatar": ""
  },
  { "name": "PlataformaLifeUA2",
    "position": 165,
    "contributions": 2,
    "public": 2,
    "private": 0,
    "bio": "",
    "followers": 3,
    "repositories":5,
    "organizations":0,
    "join": "2017-05-29",
    "avatar": ""
  },
  { "name": "pgquiles",
    "position": 166,
    "contributions": 1,
    "public": 1,
    "private": 0,
    "bio": "",
    "followers": 4,
    "repositories":31,
    "organizations":0,
    "join": "2009-10-22",
    "avatar": ""
  },
  { "name": "torrespri",
    "position": 167,
    "contributions": 1,
    "public": 1,
    "private": 0,
    "bio": "",
    "followers": 3,
    "repositories":5,
    "organizations":1,
    "join": "2010-11-16",
    "avatar": ""
  },
  { "name": "crico",
    "position": 168,
    "contributions": 1,
    "public": 1,
    "private": 0,
    "bio": "",
    "followers": 7,
    "repositories":9,
    "organizations":0,
    "join": "2010-12-28",
    "avatar": ""
  },
  { "name": "pabloangeletti",
    "position": 169,
    "contributions": 1,
    "public": 1,
    "private": 0,
    "bio": "",
    "followers": 15,
    "repositories":5,
    "organizations":0,
    "join": "2012-02-13",
    "avatar": ""
  },
  { "name": "marionety",
    "position": 170,
    "contributions": 1,
    "public": 1,
    "private": 0,
    "bio": "",
    "followers": 28,
    "repositories":9,
    "organizations":0,
    "join": "2013-07-24",
    "avatar": ""
  },
  { "name": "pocho23",
    "position": 171,
    "contributions": 1,
    "public": 1,
    "private": 0,
    "bio": "",
    "followers": 9,
    "repositories":6,
    "organizations":1,
    "join": "2013-12-27",
    "avatar": ""
  },
  { "name": "felixem",
    "position": 172,
    "contributions": 1,
    "public": 1,
    "private": 0,
    "bio": "",
    "followers": 6,
    "repositories":11,
    "organizations":0,
    "join": "2014-05-22",
    "avatar": ""
  },
  { "name": "Darky-Lucera",
    "position": 173,
    "contributions": 1,
    "public": 1,
    "private": 0,
    "bio": "",
    "followers": 3,
    "repositories":5,
    "organizations":1,
    "join": "2014-10-21",
    "avatar": ""
  },
  { "name": "petrixsoft",
    "position": 174,
    "contributions": 2,
    "public": 0,
    "private": 4,
    "bio": "",
    "followers": 2,
    "repositories":2,
    "organizations":0,
    "join": "2009-05-03",
    "avatar": ""
  },
  { "name": "webeffects",
    "position": 175,
    "contributions": 0,
    "public": 0,
    "private": 0,
    "bio": "",
    "followers": 4,
    "repositories":7,
    "organizations":0,
    "join": "2009-11-12",
    "avatar": ""
  },
  { "name": "ebarbeito",
    "position": 176,
    "contributions": 0,
    "public": 0,
    "private": 0,
    "bio": "",
    "followers": 9,
    "repositories":27,
    "organizations":1,
    "join": "2010-01-19",
    "avatar": ""
  },
  { "name": "johnsanchezc",
    "position": 177,
    "contributions": 0,
    "public": 0,
    "private": 0,
    "bio": "",
    "followers": 10,
    "repositories":36,
    "organizations":0,
    "join": "2010-04-20",
    "avatar": ""
  },
  { "name": "TraxNet",
    "position": 178,
    "contributions": 0,
    "public": 0,
    "private": 0,
    "bio": "",
    "followers": 3,
    "repositories":9,
    "organizations":0,
    "join": "2010-04-16",
    "avatar": ""
  },
  { "name": "jirubio",
    "position": 179,
    "contributions": 0,
    "public": 0,
    "private": 0,
    "bio": "",
    "followers": 2,
    "repositories":2,
    "organizations":0,
    "join": "2010-11-06",
    "avatar": ""
  },
  { "name": "perex",
    "position": 180,
    "contributions": 0,
    "public": 0,
    "private": 0,
    "bio": "",
    "followers": 10,
    "repositories":9,
    "organizations":0,
    "join": "2011-07-19",
    "avatar": ""
  },
  { "name": "isocano",
    "position": 181,
    "contributions": 0,
    "public": 0,
    "private": 0,
    "bio": "",
    "followers": 15,
    "repositories":8,
    "organizations":1,
    "join": "2011-09-29",
    "avatar": ""
  },
  { "name": "armenta-angel",
    "position": 182,
    "contributions": 0,
    "public": 0,
    "private": 0,
    "bio": "",
    "followers": 2,
    "repositories":15,
    "organizations":0,
    "join": "2011-08-13",
    "avatar": ""
  },
  { "name": "psl11",
    "position": 183,
    "contributions": 0,
    "public": 0,
    "private": 0,
    "bio": "",
    "followers": 7,
    "repositories":5,
    "organizations":1,
    "join": "2011-09-29",
    "avatar": ""
  },
  { "name": "oliver-montes",
    "position": 184,
    "contributions": 0,
    "public": 0,
    "private": 0,
    "bio": "",
    "followers": 23,
    "repositories":21,
    "organizations":0,
    "join": "2011-11-29",
    "avatar": ""
  },
  { "name": "NyoronSheppard",
    "position": 185,
    "contributions": 0,
    "public": 0,
    "private": 0,
    "bio": "",
    "followers": 3,
    "repositories":11,
    "organizations":0,
    "join": "2012-03-23",
    "avatar": ""
  },
  { "name": "Hectormm",
    "position": 186,
    "contributions": 29,
    "public": 0,
    "private": 43,
    "bio": "",
    "followers": 6,
    "repositories":18,
    "organizations":0,
    "join": "2012-05-22",
    "avatar": ""
  },
  { "name": "pablovezgz",
    "position": 187,
    "contributions": 0,
    "public": 0,
    "private": 0,
    "bio": "",
    "followers": 6,
    "repositories":4,
    "organizations":1,
    "join": "2012-04-12",
    "avatar": ""
  },
  { "name": "pablovargan",
    "position": 188,
    "contributions": 0,
    "public": 0,
    "private": 0,
    "bio": "",
    "followers": 11,
    "repositories":19,
    "organizations":1,
    "join": "2012-06-18",
    "avatar": ""
  },
  { "name": "juasiepo",
    "position": 189,
    "contributions": 0,
    "public": 0,
    "private": 0,
    "bio": "",
    "followers": 6,
    "repositories":23,
    "organizations":0,
    "join": "2012-05-30",
    "avatar": ""
  },
  { "name": "rias",
    "position": 190,
    "contributions": 0,
    "public": 0,
    "private": 0,
    "bio": "",
    "followers": 2,
    "repositories":2,
    "organizations":0,
    "join": "2012-10-17",
    "avatar": ""
  },
  { "name": "panfri787",
    "position": 191,
    "contributions": 0,
    "public": 0,
    "private": 0,
    "bio": "",
    "followers": 6,
    "repositories":8,
    "organizations":0,
    "join": "2012-07-09",
    "avatar": ""
  },
  { "name": "ConstantinoCallado",
    "position": 192,
    "contributions": 0,
    "public": 0,
    "private": 0,
    "bio": "",
    "followers": 5,
    "repositories":3,
    "organizations":0,
    "join": "2012-09-16",
    "avatar": ""
  },
  { "name": "albertogutimac",
    "position": 193,
    "contributions": 0,
    "public": 0,
    "private": 0,
    "bio": "",
    "followers": 4,
    "repositories":2,
    "organizations":0,
    "join": "2012-10-22",
    "avatar": ""
  },
  { "name": "litris",
    "position": 194,
    "contributions": 0,
    "public": 0,
    "private": 0,
    "bio": "",
    "followers": 11,
    "repositories":9,
    "organizations":0,
    "join": "2012-11-16",
    "avatar": ""
  },
  { "name": "miguelbcr",
    "position": 195,
    "contributions": 1147,
    "public": 0,
    "private": 1147,
    "bio": "",
    "followers": 32,
    "repositories":16,
    "organizations":0,
    "join": "2012-11-06",
    "avatar": ""
  },
  { "name": "LeandroMG",
    "position": 196,
    "contributions": 0,
    "public": 0,
    "private": 0,
    "bio": "",
    "followers": 5,
    "repositories":3,
    "organizations":0,
    "join": "2012-12-08",
    "avatar": ""
  },
  { "name": "Salvagm",
    "position": 197,
    "contributions": 0,
    "public": 0,
    "private": 0,
    "bio": "",
    "followers": 5,
    "repositories":6,
    "organizations":0,
    "join": "2012-11-16",
    "avatar": ""
  },
  { "name": "dviejo",
    "position": 198,
    "contributions": 0,
    "public": 0,
    "private": 0,
    "bio": "",
    "followers": 6,
    "repositories":10,
    "organizations":0,
    "join": "2013-01-21",
    "avatar": ""
  },
  { "name": "vvives",
    "position": 199,
    "contributions": 0,
    "public": 0,
    "private": 0,
    "bio": "",
    "followers": 3,
    "repositories":32,
    "organizations":0,
    "join": "2013-04-03",
    "avatar": ""
  },
  { "name": "royoruiz",
    "position": 200,
    "contributions": 0,
    "public": 0,
    "private": 0,
    "bio": "",
    "followers": 8,
    "repositories":5,
    "organizations":0,
    "join": "2013-06-21",
    "avatar": ""
  },
  { "name": "moisesbelda",
    "position": 201,
    "contributions": 0,
    "public": 0,
    "private": 0,
    "bio": "",
    "followers": 3,
    "repositories":6,
    "organizations":0,
    "join": "2013-05-26",
    "avatar": ""
  },
  { "name": "joaquindev",
    "position": 202,
    "contributions": 0,
    "public": 0,
    "private": 0,
    "bio": "",
    "followers": 10,
    "repositories":83,
    "organizations":1,
    "join": "2013-10-08",
    "avatar": ""
  },
  { "name": "albertoml",
    "position": 203,
    "contributions": 0,
    "public": 0,
    "private": 0,
    "bio": "",
    "followers": 5,
    "repositories":6,
    "organizations":0,
    "join": "2013-10-19",
    "avatar": ""
  },
  { "name": "ruarrimactire",
    "position": 204,
    "contributions": 0,
    "public": 0,
    "private": 0,
    "bio": "",
    "followers": 2,
    "repositories":9,
    "organizations":0,
    "join": "2013-11-23",
    "avatar": ""
  },
  { "name": "SergioLMacia",
    "position": 205,
    "contributions": 0,
    "public": 0,
    "private": 0,
    "bio": "",
    "followers": 3,
    "repositories":3,
    "organizations":0,
    "join": "2014-01-24",
    "avatar": ""
  },
  { "name": "david-varela",
    "position": 206,
    "contributions": 0,
    "public": 0,
    "private": 0,
    "bio": "Software engineer reorienting my career from Android development to robotics and AI",
    "followers": 2,
    "repositories":2,
    "organizations":0,
    "join": "2014-03-06",
    "avatar": ""
  },
  { "name": "fsoleraracil",
    "position": 207,
    "contributions": 0,
    "public": 0,
    "private": 0,
    "bio": "",
    "followers": 3,
    "repositories":5,
    "organizations":0,
    "join": "2014-04-14",
    "avatar": ""
  },
  { "name": "cristinarivera",
    "position": 208,
    "contributions": 0,
    "public": 0,
    "private": 0,
    "bio": "",
    "followers": 3,
    "repositories":8,
    "organizations":0,
    "join": "2014-05-22",
    "avatar": ""
  },
  { "name": "Ennaxor",
    "position": 209,
    "contributions": 0,
    "public": 0,
    "private": 0,
    "bio": "",
    "followers": 8,
    "repositories":13,
    "organizations":0,
    "join": "2014-05-27",
    "avatar": ""
  },
  { "name": "javijuol",
    "position": 210,
    "contributions": 0,
    "public": 0,
    "private": 0,
    "bio": "",
    "followers": 4,
    "repositories":24,
    "organizations":0,
    "join": "2014-05-30",
    "avatar": ""
  },
  { "name": "trackuino",
    "position": 211,
    "contributions": 0,
    "public": 0,
    "private": 0,
    "bio": "",
    "followers": 18,
    "repositories":12,
    "organizations":0,
    "join": "2014-07-25",
    "avatar": ""
  },
  { "name": "RushReckless",
    "position": 212,
    "contributions": 0,
    "public": 0,
    "private": 0,
    "bio": "",
    "followers": 3,
    "repositories":3,
    "organizations":0,
    "join": "2014-10-20",
    "avatar": ""
  },
  { "name": "sansanomir",
    "position": 213,
    "contributions": 67,
    "public": 0,
    "private": 67,
    "bio": "",
    "followers": 3,
    "repositories":6,
    "organizations":0,
    "join": "2015-01-09",
    "avatar": ""
  },
  { "name": "asalieto",
    "position": 214,
    "contributions": 0,
    "public": 0,
    "private": 0,
    "bio": "Game programmer, Multimedia Engineer.",
    "followers": 4,
    "repositories":15,
    "organizations":0,
    "join": "2014-11-19",
    "avatar": ""
  },
  { "name": "CoroVeneno",
    "position": 215,
    "contributions": 0,
    "public": 0,
    "private": 0,
    "bio": "",
    "followers": 2,
    "repositories":16,
    "organizations":0,
    "join": "2015-04-07",
    "avatar": ""
  },
  { "name": "BCasal",
    "position": 216,
    "contributions": 0,
    "public": 0,
    "private": 0,
    "bio": "",
    "followers": 5,
    "repositories":18,
    "organizations":0,
    "join": "2015-08-17",
    "avatar": ""
  },
  { "name": "adrianmantilla",
    "position": 217,
    "contributions": 0,
    "public": 0,
    "private": 0,
    "bio": "",
    "followers": 3,
    "repositories":5,
    "organizations":0,
    "join": "2015-09-22",
    "avatar": ""
  },
  { "name": "anallor",
    "position": 218,
    "contributions": 0,
    "public": 0,
    "private": 0,
    "bio": "",
    "followers": 10,
    "repositories":17,
    "organizations":0,
    "join": "2015-09-13",
    "avatar": ""
  },
  { "name": "guzmanfg",
    "position": 219,
    "contributions": 0,
    "public": 0,
    "private": 0,
    "bio": "",
    "followers": 2,
    "repositories":7,
    "organizations":0,
    "join": "2015-11-02",
    "avatar": ""
  },
  { "name": "maximusdiegus",
    "position": 220,
    "contributions": 0,
    "public": 0,
    "private": 0,
    "bio": "",
    "followers": 2,
    "repositories":5,
    "organizations":0,
    "join": "2016-03-08",
    "avatar": ""
  },
  { "name": "Rafakun",
    "position": 221,
    "contributions": 0,
    "public": 0,
    "private": 0,
    "bio": "",
    "followers": 2,
    "repositories":4,
    "organizations":0,
    "join": "2016-09-20",
    "avatar": ""
  },
  { "name": "DavidBerbegal",
    "position": 222,
    "contributions": 0,
    "public": 0,
    "private": 0,
    "bio": "",
    "followers": 2,
    "repositories":2,
    "organizations":0,
    "join": "2016-03-21",
    "avatar": ""
  },
  { "name": "devochka",
    "position": 223,
    "contributions": 0,
    "public": 0,
    "private": 0,
    "bio": "",
    "followers": 7,
    "repositories":14,
    "organizations":0,
    "join": "2016-10-31",
    "avatar": ""
  },
  { "name": "salvatv",
    "position": 224,
    "contributions": 0,
    "public": 0,
    "private": 0,
    "bio": "",
    "followers": 4,
    "repositories":10,
    "organizations":0,
    "join": "2017-07-11",
    "avatar": ""
  }
  ]
}
